comdaan/__init__.py
comdaan/comdaan.py
comdaan/comdaan_fetch.py
comdaan/display.py
comdaan/gitparsing.py
comdaan/issuesparsing.py
comdaan/mailparsing.py
comdaan/object_types.py
comdaan/rulesetfinding.py
comdaan/rulesets/kde.py
comdaan-0.1.13.dist-info/METADATA
comdaan-0.1.13.dist-info/WHEEL
comdaan-0.1.13.dist-info/entry_points.txt
comdaan-0.1.13.dist-info/licenses/LICENSE
comdaan-0.1.13.dist-info/RECORD
