Metadata-Version: 2.4
Name: ComDaAn
Version: 0.1.13
Summary: This is a suite of tools for conducting analysis from data produced by FOSS communities. This is currently mainly focusing on git repositories.
Project-URL: repository, https://framagit.org/ervin/ComDaAn/
Project-URL: Issues, https://framagit.org/ervin/ComDaAn/-/issues
Author-email: Kevin Ottens <ervin@ipsquad.net>, Christelle Zouein <christelle.zouein@epita.fr>, Frederik Gladhorn <frederik.gladhorn@qt.io>, Benson Muite <benson_muite@emailplus.org>
License:                                  Apache License
License-File: LICENSE
Keywords: analysis,data,git,repositories
Classifier: License :: OSI Approved :: Apache Software License
Classifier: Operating System :: OS Independent
Classifier: Programming Language :: Python :: 3
Requires-Python: >=3.10
Requires-Dist: bokeh~=3.6
Requires-Dist: multiprocess~=0.70
Requires-Dist: networkx~=3.4
Requires-Dist: pandas~=2.2
Requires-Dist: python-gitlab~=5.3
Requires-Dist: scipy~=1.15
Requires-Dist: statsmodels~=0.14
